vrmjobs/__init__.py
vrmjobs/__version__.py
vrmjobs/filter_info.py
vrmjobs/host_info.py
vrmjobs/host_type.py
vrmjobs/metric_info.py
vrmjobs/port_info.py
vrmjobs/probe_ack.py
vrmjobs/probe_init.py
vrmjobs/register_ack.py
vrmjobs/register_info.py
vrmjobs/report_init.py
vrmjobs/vrm_type.py
tl_vrmjobs-3.0.1.dist-info/LICENSE
tl_vrmjobs-3.0.1.dist-info/METADATA
tl_vrmjobs-3.0.1.dist-info/WHEEL
tl_vrmjobs-3.0.1.dist-info/top_level.txt
tl_vrmjobs-3.0.1.dist-info/RECORD
