Metadata-Version: 2.1
Name: tl-vrmjobs
Version: 3.0.1
Summary: Job classes used in VRM cloudless system
Home-page: https://github.com/thanhledev/vrmjobs
Author: Thanh Le
Author-email: thanhledev@gmail.com
License: MIT
Platform: UNKNOWN
Classifier: License :: OSI Approved :: MIT License
Classifier: Programming Language :: Python
Classifier: Programming Language :: Python :: 3
Classifier: Programming Language :: Python :: 3.6
Requires-Python: >=3.6.0
